csmpe/__init__.py
csmpe/__main__.py
csmpe/context.py
csmpe/csm_pm.py
csmpe/decorators.py
csmpe/core_plugins/__init__.py
csmpe/core_plugins/csm_check_config_filesystem/__init__.py
csmpe/core_plugins/csm_check_config_filesystem/ios_xr/__init__.py
csmpe/core_plugins/csm_check_config_filesystem/ios_xr/plugin.py
csmpe/core_plugins/csm_check_isis_neighbors/__init__.py
csmpe/core_plugins/csm_check_isis_neighbors/ios_xr/__init__.py
csmpe/core_plugins/csm_check_isis_neighbors/ios_xr/plugin.py
csmpe/core_plugins/csm_config_capture/__init__.py
csmpe/core_plugins/csm_config_capture/plugin.py
csmpe/core_plugins/csm_custom_commands_capture/__init__.py
csmpe/core_plugins/csm_custom_commands_capture/plugin.py
csmpe/core_plugins/csm_error_core_check/__init__.py
csmpe/core_plugins/csm_error_core_check/ios_xr/__init__.py
csmpe/core_plugins/csm_error_core_check/ios_xr/plugin.py
csmpe/core_plugins/csm_failed_config_startup_check/__init__.py
csmpe/core_plugins/csm_failed_config_startup_check/ios_xr/__init__.py
csmpe/core_plugins/csm_failed_config_startup_check/ios_xr/plugin.py
csmpe/core_plugins/csm_filesystem_check/__init__.py
csmpe/core_plugins/csm_filesystem_check/ios_xr/__init__.py
csmpe/core_plugins/csm_filesystem_check/ios_xr/disk_space_check.py
csmpe/core_plugins/csm_filesystem_check/ios_xr/filesystem_rw_check.py
csmpe/core_plugins/csm_filesystem_check/ios_xr/utils.py
csmpe/core_plugins/csm_get_inventory/__init__.py
csmpe/core_plugins/csm_get_inventory/exr/__init__.py
csmpe/core_plugins/csm_get_inventory/exr/plugin.py
csmpe/core_plugins/csm_get_inventory/ios/__init__.py
csmpe/core_plugins/csm_get_inventory/ios/plugin.py
csmpe/core_plugins/csm_get_inventory/ios_xe/__init__.py
csmpe/core_plugins/csm_get_inventory/ios_xe/plugin.py
csmpe/core_plugins/csm_get_inventory/ios_xr/__init__.py
csmpe/core_plugins/csm_get_inventory/ios_xr/plugin.py
csmpe/core_plugins/csm_get_inventory/nx_os/__init__.py
csmpe/core_plugins/csm_get_inventory/nx_os/plugin.py
csmpe-0.1.4.dist-info/DESCRIPTION.rst
csmpe-0.1.4.dist-info/entry_points.txt
csmpe-0.1.4.dist-info/METADATA
csmpe-0.1.4.dist-info/metadata.json
csmpe-0.1.4.dist-info/RECORD
csmpe-0.1.4.dist-info/top_level.txt
csmpe-0.1.4.dist-info/WHEEL
